huaweicloudsdkevs/__init__.py
huaweicloudsdkevs/v2/__init__.py
huaweicloudsdkevs/v2/evs_async_client.py
huaweicloudsdkevs/v2/evs_client.py
huaweicloudsdkevs/v2/model/__init__.py
huaweicloudsdkevs/v2/model/attachment.py
huaweicloudsdkevs/v2/model/az_info.py
huaweicloudsdkevs/v2/model/batch_create_volume_tags_request.py
huaweicloudsdkevs/v2/model/batch_create_volume_tags_request_body.py
huaweicloudsdkevs/v2/model/batch_create_volume_tags_response.py
huaweicloudsdkevs/v2/model/batch_delete_volume_tags_request.py
huaweicloudsdkevs/v2/model/batch_delete_volume_tags_request_body.py
huaweicloudsdkevs/v2/model/batch_delete_volume_tags_response.py
huaweicloudsdkevs/v2/model/batch_resize_volume_request_body.py
huaweicloudsdkevs/v2/model/batch_resize_volumes_request.py
huaweicloudsdkevs/v2/model/batch_resize_volumes_response.py
huaweicloudsdkevs/v2/model/bss_param_for_create_volume.py
huaweicloudsdkevs/v2/model/bss_param_for_resize_volume.py
huaweicloudsdkevs/v2/model/bss_param_for_retype_volume.py
huaweicloudsdkevs/v2/model/cinder_accept_volume_transfer_option.py
huaweicloudsdkevs/v2/model/cinder_accept_volume_transfer_request.py
huaweicloudsdkevs/v2/model/cinder_accept_volume_transfer_request_body.py
huaweicloudsdkevs/v2/model/cinder_accept_volume_transfer_response.py
huaweicloudsdkevs/v2/model/cinder_create_volume_transfer_request.py
huaweicloudsdkevs/v2/model/cinder_create_volume_transfer_request_body.py
huaweicloudsdkevs/v2/model/cinder_create_volume_transfer_response.py
huaweicloudsdkevs/v2/model/cinder_delete_volume_transfer_request.py
huaweicloudsdkevs/v2/model/cinder_delete_volume_transfer_response.py
huaweicloudsdkevs/v2/model/cinder_list_availability_zones_request.py
huaweicloudsdkevs/v2/model/cinder_list_availability_zones_response.py
huaweicloudsdkevs/v2/model/cinder_list_quotas_request.py
huaweicloudsdkevs/v2/model/cinder_list_quotas_response.py
huaweicloudsdkevs/v2/model/cinder_list_volume_transfers_request.py
huaweicloudsdkevs-3.1.184.dist-info/METADATA
huaweicloudsdkevs-3.1.184.dist-info/WHEEL
huaweicloudsdkevs-3.1.184.dist-info/licenses/LICENSE
huaweicloudsdkevs-3.1.184.dist-info/RECORD
